manifest/__init__.py
manifest/core/__init__.py
manifest/core/exceptions.py
manifest/core/loader.py
manifest/core/models.py
manifest/core/service.py
manifest/core/services.py
manifest/infrastructure/__init__.py
manifest/infrastructure/bootstrap/__init__.py
manifest/infrastructure/bootstrap/bootstrap.py
manifest/infrastructure/registry/__init__.py
manifest/infrastructure/registry/registry.py
manifest/interfaces/__init__.py
manifest/interfaces/cli/__init__.py
manifest/interfaces/cli/commands.py
manifest/interfaces/cli/formatters.py
manifest/interfaces/mcp/__init__.py
manifest/interfaces/mcp/resources.py
manifest/interfaces/mcp/tools.py
manifest/interfaces/rest/__init__.py
manifest/interfaces/rest/middleware.py
manifest/interfaces/rest/models.py
manifest/interfaces/rest/routes.py
chora_manifest-0.1.1.dist-info/METADATA
chora_manifest-0.1.1.dist-info/WHEEL
chora_manifest-0.1.1.dist-info/entry_points.txt
chora_manifest-0.1.1.dist-info/top_level.txt
chora_manifest-0.1.1.dist-info/RECORD
