Metadata-Version: 2.4
Name: chora-manifest
Version: 0.1.1
Summary: MCP server service discovery - Read-only Python library for querying MCP server capabilities
Author-email: Liminal Commons <team@liminalcommons.org>
License: MIT
Project-URL: Homepage, https://github.com/yourusername/manifest
Project-URL: Documentation, https://manifest.readthedocs.io
Project-URL: Repository, https://github.com/yourusername/manifest
Project-URL: Issues, https://github.com/yourusername/manifest/issues
Project-URL: Changelog, https://github.com/yourusername/manifest/blob/main/CHANGELOG.md
Keywords: mcp,model-context-protocol,service-discovery,capability-catalog,manifest
Classifier: Development Status :: 3 - Alpha
Classifier: Intended Audience :: Developers
Classifier: License :: OSI Approved :: MIT License
Classifier: Programming Language :: Python :: 3
Classifier: Programming Language :: Python :: 3.11
Classifier: Programming Language :: Python :: 3.12
Classifier: Programming Language :: Python :: 3.13
Classifier: Topic :: Software Development :: Libraries :: Python Modules
Classifier: Typing :: Typed
Requires-Python: >=3.11
Requires-Dist: pydantic<3.0.0,>=2.0.0
Requires-Dist: pydantic-settings<3.0.0,>=2.0.0
Requires-Dist: pyyaml<7.0.0,>=6.0.0
Provides-Extra: dev
Requires-Dist: pytest<9.0.0,>=8.0.0; extra == "dev"
Requires-Dist: pytest-asyncio<1.0.0,>=0.23.0; extra == "dev"
Requires-Dist: pytest-cov<5.0.0,>=4.1.0; extra == "dev"
Requires-Dist: pytest-timeout<3.0.0,>=2.2.0; extra == "dev"
Requires-Dist: pytest-xdist<4.0.0,>=3.5.0; extra == "dev"
Requires-Dist: pytest-httpx<1.0.0,>=0.30.0; extra == "dev"
Requires-Dist: httpx<1.0.0,>=0.27.0; extra == "dev"
Requires-Dist: ruff<1.0.0,>=0.3.0; extra == "dev"
Requires-Dist: mypy<2.0.0,>=1.9.0; extra == "dev"
Requires-Dist: pre-commit<4.0.0,>=3.6.0; extra == "dev"
Requires-Dist: mkdocs<2.0.0,>=1.5.0; extra == "dev"
Requires-Dist: mkdocs-material<10.0.0,>=9.5.0; extra == "dev"
Requires-Dist: mkdocstrings[python]<1.0.0,>=0.24.0; extra == "dev"
Provides-Extra: docker
Requires-Dist: gunicorn<22.0.0,>=21.2.0; extra == "docker"
